BharatFinTrack/__init__.py
BharatFinTrack/core.py
BharatFinTrack/nse_index.py
BharatFinTrack/nse_product.py
BharatFinTrack/nse_tri.py
BharatFinTrack/visual.py
BharatFinTrack/data/equity_indices.xlsx
bharatfintrack-0.2.2.dist-info/licenses/LICENSE
bharatfintrack-0.2.2.dist-info/METADATA
bharatfintrack-0.2.2.dist-info/WHEEL
bharatfintrack-0.2.2.dist-info/top_level.txt
bharatfintrack-0.2.2.dist-info/RECORD
