Metadata-Version: 2.4
Name: BharatFinTrack
Version: 0.2.2
Summary: Downloading and analyzing financial data, including indices, stocks, bonds, and mutual funds, from India, that is Bharat.
Author-email: Debasish Pal <bestdebasish@gmail.com>
License-Expression: MIT
Project-URL: Homepage, https://github.com/debpal/BharatFinTrack
Project-URL: Documentation, https://bharatfintrack.readthedocs.io/en/latest/
Keywords: NSE Index,Download,CAGR,SIP,Visualization
Classifier: Development Status :: 5 - Production/Stable
Classifier: Programming Language :: Python :: 3.13
Classifier: Programming Language :: Python :: 3.12
Classifier: Programming Language :: Python :: 3.11
Classifier: Programming Language :: Python :: 3.10
Classifier: Operating System :: OS Independent
Classifier: Intended Audience :: Education
Classifier: Intended Audience :: Financial and Insurance Industry
Classifier: Topic :: Office/Business :: Financial
Classifier: Topic :: Office/Business :: Financial :: Investment
Classifier: Topic :: Scientific/Engineering :: Information Analysis
Requires-Python: >=3.10
License-File: LICENSE
Requires-Dist: pandas
Requires-Dist: requests
Requires-Dist: openpyxl
Requires-Dist: xlsxwriter
Requires-Dist: beautifulsoup4
Requires-Dist: matplotlib
Requires-Dist: pyxirr
Dynamic: license-file
